aioredlock/__init__.py
aioredlock/algorithm.py
aioredlock/errors.py
aioredlock/lock.py
aioredlock/redis.py
aioredlock_neorisk-0.4.0.dist-info/LICENSE.md
aioredlock_neorisk-0.4.0.dist-info/METADATA
aioredlock_neorisk-0.4.0.dist-info/WHEEL
aioredlock_neorisk-0.4.0.dist-info/top_level.txt
aioredlock_neorisk-0.4.0.dist-info/RECORD
