Metadata-Version: 2.1
Name: aioredlock-neorisk
Version: 0.4.0
Summary: Asyncio implemetation of Redis distributed locks (Neorisk)
Home-page: https://github.com/neorisk/aioredlock
Author: Joan Vilà Cuñat
Author-email: vila.joan94@gmail.com
License: MIT
Keywords: redis redlock distributed locks asyncio
Platform: UNKNOWN
Classifier: Development Status :: 4 - Beta
Classifier: Intended Audience :: Developers
Classifier: Topic :: Software Development :: Libraries :: Python Modules
Classifier: License :: OSI Approved :: MIT License
Classifier: Programming Language :: Python :: 3.5
Classifier: Programming Language :: Python :: 3.6
Requires-Dist: aioredis
Requires-Dist: attrs (>=17.4.0)
